{
    "version": 1,
    "size": {
        "x": 32,
        "y": 32
    },
	"license": "CC-BY-SA-4.0",
    "copyright": "Taken from CDDA tileset Ultimate Cataclysm, modified by zeranov/avtomata (disc:core_mene)",
    "states": [
        {
            "name": "fence_0"

        },
        {
            "name": "fence_1"

        },
        {
            "name": "fence_2"

        },
        {
            "name": "fence_3"

        },
        {
            "name": "fence_4"

        },
        {
            "name": "fence_5"

        },
        {
            "name": "fence_6"

        },
        {
            "name": "fence_7"

        },
        {
            "name": "fence_8"

        },
        {
            "name": "fence_9"

        },
        {
            "name": "fence_10"

        },
        {
            "name": "fence_11"

        },
        {
            "name": "fence_12"

        },
        {
            "name": "fence_13"

        },
        {
            "name": "fence_14"

        },
        {
            "name": "fence_15"

        }
    ]
}
